README.md
setup.py
ffmpeg/__init__.py
ffmpeg/_dag.py
ffmpeg/_ffmpeg.py
ffmpeg/_ffplay.py
ffmpeg/_ffprobe.py
ffmpeg/_node.py
ffmpeg/_utils.py
ffmpeg/constants.py
ffmpeg/nodes.py
ffmpeg/settings.py
ffmpeg/expression/__init__.py
ffmpeg/expression/layout.py
ffmpeg/filters/__init__.py
ffmpeg/filters/afilters.py
ffmpeg/filters/avfilters.py
ffmpeg/filters/vfilters.py
ffmpeg/tools/__init__.py
ffmpeg/tools/atools.py
ffmpeg/tools/avtools.py
ffmpeg/tools/etools.py
ffmpeg/tools/vtools.py
ffmpeg/transitions/__init__.py
ffmpeg/transitions/_gltransition.py
ffmpeg/transitions/_xfade.py
ffmpeg/transitions/glsl/Bounce.glsl
ffmpeg/transitions/glsl/BowTieHorizontal.glsl
ffmpeg/transitions/glsl/BowTieVertical.glsl
ffmpeg/transitions/glsl/BowTieWithParameter.glsl
ffmpeg/transitions/glsl/ButterflyWaveScrawler.glsl
ffmpeg/transitions/glsl/CircleCrop.glsl
ffmpeg/transitions/glsl/ColourDistance.glsl
ffmpeg/transitions/glsl/CrazyParametricFun.glsl
ffmpeg/transitions/glsl/CrossZoom.glsl
ffmpeg/transitions/glsl/Directional.glsl
ffmpeg/transitions/glsl/DoomScreenTransition.glsl
ffmpeg/transitions/glsl/Dreamy.glsl
ffmpeg/transitions/glsl/DreamyZoom.glsl
ffmpeg/transitions/glsl/FilmBurn.glsl
ffmpeg/transitions/glsl/GlitchDisplace.glsl
ffmpeg/transitions/glsl/GlitchMemories.glsl
ffmpeg/transitions/glsl/GridFlip.glsl
ffmpeg/transitions/glsl/InvertedPageCurl.glsl
ffmpeg/transitions/glsl/LeftRight.glsl
ffmpeg/transitions/glsl/LinearBlur.glsl
ffmpeg/transitions/glsl/Mosaic.glsl
ffmpeg/transitions/glsl/PolkaDotsCurtain.glsl
ffmpeg/transitions/glsl/Radial.glsl
ffmpeg/transitions/glsl/SimpleZoom.glsl
ffmpeg/transitions/glsl/StereoViewer.glsl
ffmpeg/transitions/glsl/Swirl.glsl
ffmpeg/transitions/glsl/TVStatic.glsl
ffmpeg/transitions/glsl/TopBottom.glsl
ffmpeg/transitions/glsl/WaterDrop.glsl
ffmpeg/transitions/glsl/ZoomInCircles.glsl
ffmpeg/transitions/glsl/angular.glsl
ffmpeg/transitions/glsl/burn.glsl
ffmpeg/transitions/glsl/cannabisleaf.glsl
ffmpeg/transitions/glsl/circle.glsl
ffmpeg_generator.egg-info/PKG-INFO
ffmpeg_generator.egg-info/SOURCES.txt
ffmpeg_generator.egg-info/dependency_links.txt
ffmpeg_generator.egg-info/requires.txt
ffmpeg_generator.egg-info/top_level.txt