Metadata-Version: 2.1
Name: ffmpeg-generator
Version: 1.0.6
Summary: Python bindings for FFmpeg - with almost all filters support, even `gltransition` filter.
Home-page: https://github.com/fujiawei-dev/ffmpeg-generator
Author: Rustle Karl
Author-email: fu.jiawei@outlook.com
License: MIT
Keywords: ffmpeg,ffprobe,ffplay
Platform: UNKNOWN
Classifier: Intended Audience :: Developers
Classifier: License :: OSI Approved :: MIT License
Classifier: Operating System :: OS Independent
Classifier: Programming Language :: Python :: 3.8
Classifier: Programming Language :: Python :: 3.9
